{
  "symbol": "AMWD",
  "price": 39.2023,
  "marketCap": 571161634,
  "beta": 1.274,
  "lastDividend": 0,
  "range": "38.31-72.16",
  "change": 0.0823,
  "changePercentage": 0.21038,
  "volume": 59092.46206,
  "averageVolume": 176855,
  "companyName": "American Woodmark Corporation",
  "currency": "USD",
  "cik": "0000794619",
  "isin": "US0305061097",
  "cusip": "030506109",
  "exchangeFullName": "NASDAQ Global Select",
  "exchange": "NASDAQ",
  "industry": "Furnishings, Fixtures & Appliances",
  "website": "https://www.americanwoodmark.com",
  "description": "American Woodmark Corporation manufactures and distributes kitchen, bath, office, home organization, and hardware products for the remodelling and new home construction markets in the United States. The company offers made-to-order and cash and carry products. It also provides turnkey installation services to its direct builder customers through a network of eight service centers. The company sells its products under the American Woodmark, Timberlake, Shenandoah Cabinetry, Waypoint Living Spaces, Estate, Stor-It-All, and Professional Cabinet Solutions brands, as well as Hampton Bay, Glacier Bay, Style Selections, Allen + Roth, Home Decorators Collection, and Project Source. It markets its products directly to home centers and builders, as well as through independent dealers and distributors. The company was incorporated in 1980 and is based in Winchester, Virginia.",
  "ceo": "Michael Scott Culbreth",
  "sector": "Consumer Cyclical",
  "country": "US",
  "fullTimeEmployees": "8600",
  "phone": "540 665 9100",
  "address": "561 Shady Elm Road",
  "city": "Winchester",
  "state": "VA",
  "zip": "22602",
  "image": "https://images.financialmodelingprep.com/symbol/AMWD.png",
  "ipoDate": "1986-07-18",
  "defaultImage": false,
  "isEtf": false,
  "isActivelyTrading": true,
  "isAdr": false,
  "isFund": false
}