{
  "symbol": "PETQ",
  "price": 30.98,
  "marketCap": 919170404,
  "beta": 1.736,
  "lastDividend": 0,
  "range": "15.09-31.06",
  "change": -0.01,
  "changePercentage": -0.0323,
  "volume": 928270,
  "averageVolume": 944807,
  "companyName": "PetIQ, Inc.",
  "currency": "USD",
  "cik": "0001668673",
  "isin": "US71639T1060",
  "cusip": "71639T106",
  "exchangeFullName": "NASDAQ Global Select",
  "exchange": "NASDAQ",
  "industry": "Drug Manufacturers - Specialty & Generic",
  "website": "https://petiq.com",
  "description": "PetIQ, Inc. operates as a pet medication and wellness company in the United States and internationally. It operates in two segments, Products and Services. The company offers Rx pet medications, which include flea and tick control, heartworm preventatives, arthritis, thyroid, diabetes and pain treatments, antibiotics, and other specialty medications; and develops and manufactures its own proprietary value-branded products, as well as distributes third-party branded medications. It also provides OTC medications and supplies primarily within the flea and tick control, and behavior management categories of the health and wellness industry in various forms, such as spot on (topical) treatments, chewables, oral tablets, and collars. In addition, the company offers health and wellness products that include dental treats and nutritional supplements, which comprise hip and joint, vitamins, and skin and coat products. The company provides its products primarily under the PetIQ, PetArmor, VIP Petcare, VetIQ PetCare, VetIQ, Capstar, Advecta, SENTRY, Sergeants, PetLock, Heart Shield Plus, TruProfen, Betsy Farms, PetAction, Minties, Vera, and Delightibles brands. In addition, the company offers a suite of services at 2,900 community clinics and wellness centers hosted at pet retailers across 42 states, including diagnostic tests, vaccinations, prescription medications, microchipping, and wellness checks. It operates through approximately 60,000 points of distribution across veterinarian, retail, and e-commerce channels. The company was founded in 2010 and is headquartered in Eagle, Idaho.",
  "ceo": "McCord Christensen",
  "sector": "Healthcare",
  "country": "US",
  "fullTimeEmployees": "1121",
  "phone": "208 939 8900",
  "address": "230 East Riverside Drive",
  "city": "Eagle",
  "state": "ID",
  "zip": "83616",
  "image": "https://images.financialmodelingprep.com/symbol/PETQ.png",
  "ipoDate": "2017-07-21",
  "defaultImage": false,
  "isEtf": false,
  "isActivelyTrading": false,
  "isAdr": false,
  "isFund": false
}