{
  "symbol": "VTEX",
  "price": 3.905,
  "marketCap": 701433043,
  "beta": 1.311,
  "lastDividend": 0,
  "range": "2.841-6.82",
  "change": -0.05500003,
  "changePercentage": -1.38889,
  "volume": 210893,
  "averageVolume": 1071122,
  "companyName": "Vtex",
  "currency": "USD",
  "cik": "0001793663",
  "isin": "KYG9470A1022",
  "cusip": "G9470A102",
  "exchangeFullName": "New York Stock Exchange",
  "exchange": "NYSE",
  "industry": "Software - Application",
  "website": "https://www.vtex.com",
  "description": "VTEX provides software-as-a-service digital commerce platform for enterprise brands and retailers. Its platform enables customers to execute their commerce strategy, including building online stores, integrating, and managing orders across channels, and creating marketplaces to sell products from third-party vendors. It has operations in Brazil, Argentina, Chile, Colombia, France, Italy, Mexico, Peru, Portugal, Romania, Spain, the United Kingdom, and the United States. VTEX was founded in 2000 and is headquartered in London, the United Kingdom.",
  "ceo": "Geraldo do Carmo Thomaz Jr.",
  "sector": "Technology",
  "country": "GB",
  "fullTimeEmployees": "1368",
  "phone": "44 20 3695 7895",
  "address": "Aviation House",
  "city": "London",
  "state": null,
  "zip": "WC2B 6NH",
  "image": "https://images.financialmodelingprep.com/symbol/VTEX.png",
  "ipoDate": "2021-07-21",
  "defaultImage": false,
  "isEtf": false,
  "isActivelyTrading": true,
  "isAdr": false,
  "isFund": false
}